napari_merge_stardist_masks/__init__.py
napari_merge_stardist_masks/_sample_data.py
napari_merge_stardist_masks/_version.py
napari_merge_stardist_masks/_widget.py
napari_merge_stardist_masks/napari.yaml
napari_merge_stardist_masks/_tests/__init__.py
napari_merge_stardist_masks/_tests/test_sample_data.py
napari_merge_stardist_masks/_tests/test_widget.py
napari_merge_stardist_masks/data/biofilm_1_cropped_again_raw.tif
napari_merge_stardist_masks-0.1.1.dist-info/LICENSE
napari_merge_stardist_masks-0.1.1.dist-info/METADATA
napari_merge_stardist_masks-0.1.1.dist-info/WHEEL
napari_merge_stardist_masks-0.1.1.dist-info/entry_points.txt
napari_merge_stardist_masks-0.1.1.dist-info/top_level.txt
napari_merge_stardist_masks-0.1.1.dist-info/RECORD
