Metadata-Version: 2.1
Name: napari-merge-stardist-masks
Version: 0.1.1
Summary: Segment non-star-convex objects with StarDist by merging masks.
Home-page: https://github.com/gatoniel/napari-merge-stardist-masks
Author: Niklas Netter
Author-email: niknett@gmail.com
License: BSD-3-Clause
Project-URL: Bug Tracker, https://github.com/gatoniel/napari-merge-stardist-masks/issues
Project-URL: Documentation, https://github.com/gatoniel/napari-merge-stardist-masks#README.md
Project-URL: Source Code, https://github.com/gatoniel/napari-merge-stardist-masks
Project-URL: User Support, https://github.com/gatoniel/napari-merge-stardist-masks/issues
Classifier: Development Status :: 2 - Pre-Alpha
Classifier: Framework :: napari
Classifier: Intended Audience :: Developers
Classifier: License :: OSI Approved :: BSD License
Classifier: Operating System :: OS Independent
Classifier: Programming Language :: Python
Classifier: Programming Language :: Python :: 3
Classifier: Programming Language :: Python :: 3 :: Only
Classifier: Programming Language :: Python :: 3.8
Classifier: Programming Language :: Python :: 3.9
Classifier: Programming Language :: Python :: 3.10
Classifier: Topic :: Scientific/Engineering :: Image Processing
Requires-Python: >=3.8
License-File: LICENSE
Requires-Dist: numpy
Requires-Dist: magicgui
Requires-Dist: qtpy
Requires-Dist: importlib-resources
Requires-Dist: stardist-napari >=2022.7.5
Requires-Dist: merge-stardist-masks >=0.1.0
Provides-Extra: testing
Requires-Dist: tox ; extra == 'testing'
Requires-Dist: pytest ; extra == 'testing'
Requires-Dist: pytest-cov ; extra == 'testing'
Requires-Dist: pytest-qt ; extra == 'testing'
Requires-Dist: napari ; extra == 'testing'
Requires-Dist: pyqt5 ; extra == 'testing'
